functiontester/__init__.py
functiontester/functiontester.py
FunctionTester-0.1.1.dist-info/LICENSE.txt
FunctionTester-0.1.1.dist-info/METADATA
FunctionTester-0.1.1.dist-info/WHEEL
FunctionTester-0.1.1.dist-info/top_level.txt
FunctionTester-0.1.1.dist-info/RECORD
