Metadata-Version: 2.1
Name: FunctionTester
Version: 0.1.1
Summary: A python library that allows you to easily test functions in your code
Home-page: https://github.com/Fort-P/functiontester
Author: Fort-P
License: MIT
Platform: UNKNOWN
License-File: LICENSE.txt
